recommendation1000Movies-1.data/data/movie_summaries.json
recommendation1000Movies-1.data/data/movie_vectors.json
recommending_movies/__init__.py
recommending_movies/movie_recommendations.py
recommending_movies/data/movie_summaries.json
recommending_movies/data/movie_vectors.json
recommendation1000Movies-1.dist-info/LICENSE
recommendation1000Movies-1.dist-info/METADATA
recommendation1000Movies-1.dist-info/WHEEL
recommendation1000Movies-1.dist-info/entry_points.txt
recommendation1000Movies-1.dist-info/top_level.txt
recommendation1000Movies-1.dist-info/RECORD
